[
  [
    {
      "prediction": "In the modern era of automation and robotics, autonomous vehicles are currently the focus of academic and industrial research.",
      "metrics": {
        "sari": 9.839973496960793,
        "bleu": 14.051676978912429,
        "fkgl": 15.638095238095236,
        "in_tokens": 0,
        "out_tokens": 0
      }
    },
    {
      "prediction": "In the modern era of automation and robotics, researchers are studying autonomous vehicles in both academia and industry.",
      "metrics": {
        "sari": 25.410500525443055,
        "bleu": 4.814971807094068,
        "fkgl": 15.220000000000002,
        "in_tokens": 5138,
        "out_tokens": 302
      }
    },
    {
      "prediction": "In the modern era of automation and robotics, researchers are studying autonomous vehicles in both academia and industry.",
      "metrics": {
        "sari": 25.410500525443055,
        "bleu": 4.814971807094068,
        "fkgl": 15.220000000000002,
        "in_tokens": 15114,
        "out_tokens": 606
      }
    },
    {
      "prediction": "In the modern era of automation and robotics, researchers are studying autonomous vehicles in both academia and industry.",
      "metrics": {
        "sari": 25.410500525443055,
        "bleu": 4.814971807094068,
        "fkgl": 15.220000000000002,
        "in_tokens": 30036,
        "out_tokens": 915
      }
    },
    {
      "prediction": "In the modern era of automation and robotics, Researchers are studying self-driving cars in both schools and businesses.",
      "metrics": {
        "sari": 22.36117330944917,
        "bleu": 2.5197593442434796,
        "fkgl": 11.68,
        "in_tokens": 49939,
        "out_tokens": 1234
      }
    }
  ],
  [
    {
      "prediction": "With the ever increasing number of unmanned aerial vehicles getting involved in activities in the civilian and commercial domain, there is an increased need for autonomy in these systems too.",
      "metrics": {
        "sari": 9.17143246187364,
        "bleu": 15.356865413172349,
        "fkgl": 18.277500000000007,
        "in_tokens": 0,
        "out_tokens": 0
      }
    }
  ],
  [
    {
      "prediction": "Due to guidelines set by the governments regarding the operation ceiling of civil drones, road-tracking based navigation is garnering interest.",
      "metrics": {
        "sari": 20.187097822213836,
        "bleu": 41.58468660054065,
        "fkgl": 15.51727272727273,
        "in_tokens": 0,
        "out_tokens": 0
      }
    },
    {
      "prediction": "Due to guidelines set by the governments regarding the operation ceiling of civil drones, road-tracking based navigation is garnering interest.",
      "metrics": {
        "sari": 20.187097822213836,
        "bleu": 41.58468660054065,
        "fkgl": 15.51727272727273,
        "in_tokens": 4671,
        "out_tokens": 180
      }
    },
    {
      "prediction": "Due to guidelines set by the governments regarding the operation ceiling of civil drones, tracking navigation is garnering interest.",
      "metrics": {
        "sari": 19.790248924385413,
        "bleu": 29.52818889864951,
        "fkgl": 14.514285714285716,
        "in_tokens": 13082,
        "out_tokens": 334
      }
    }
  ],
  [
    {
      "prediction": "In an attempt to achieve the above mentioned tasks, we propose an imitation learning based, data-driven solution to UAV autonomy for navigating through city streets by learning to fly by imitating an expert pilot.",
      "metrics": {
        "sari": 13.418803418803419,
        "bleu": 24.455861610699284,
        "fkgl": 18.612972972972972,
        "in_tokens": 0,
        "out_tokens": 0
      }
    }
  ],
  [
    {
      "prediction": "Derived from the classic image classification algorithms, our classifier has been constructed in the form of a fast 39-layered Inception model, that evaluates the presence of roads using the tomographic reconstructions of the input frames.",
      "metrics": {
        "sari": 9.165100804326121,
        "bleu": 10.947127056200989,
        "fkgl": 19.48,
        "in_tokens": 0,
        "out_tokens": 0
      }
    },
    {
      "prediction": "Derived from the classic image classification algorithms, our classifier has been made as a simplified 39-layered Inception model, that evaluates the presence of roads using the tomographic reconstructions of the input frames.",
      "metrics": {
        "sari": 24.59735759968045,
        "bleu": 11.87311958200751,
        "fkgl": 18.93189189189189,
        "in_tokens": 4767,
        "out_tokens": 226
      }
    },
    {
      "prediction": "Derived from the classic image classification algorithms, our classifier has been made as a simplified a 39-layered model, that evaluates the presence of roads using the tomographic reconstructions of the input frames.",
      "metrics": {
        "sari": 25.427118634198603,
        "bleu": 10.146459445560989,
        "fkgl": 18.294054054054055,
        "in_tokens": 13530,
        "out_tokens": 418
      }
    }
  ]
]